{"name":"我的超现实主义人生","postlist":[{"title":"对话游戏","slug":"对话游戏","date":"2021-02-10T10:49:10.000Z","updated":"2021-03-07T10:23:25.565Z","comments":true,"path":"api/articles/对话游戏.json","excerpt":null,"keywords":null,"cover":null,"content":null,"raw":null,"categories":[{"name":"坐在夕阳下的思考","path":"api/categories/坐在夕阳下的思考.json"}],"tags":[{"name":"我的超现实主义人生","path":"api/tags/我的超现实主义人生.json"}]},{"title":"这就是我的信条","slug":"这就是我的信条","date":"2021-02-21T12:36:02.000Z","updated":"2021-02-21T14:37:48.794Z","comments":true,"path":"api/articles/这就是我的信条.json","excerpt":null,"keywords":null,"cover":"/2021/02/%E8%BF%99%E5%B0%B1%E6%98%AF%E6%88%91%E7%9A%84%E4%BF%A1%E6%9D%A1/p2618994146.webp","content":null,"raw":null,"categories":[{"name":"坐在夕阳下的思考","path":"api/categories/坐在夕阳下的思考.json"}],"tags":[{"name":"我的超现实主义人生","path":"api/tags/我的超现实主义人生.json"}]}]}