{"name":"搭建博客","postlist":[{"title":"博客同时部署到github和gitee","slug":"博客同时部署到github和gitee","date":"2021-01-18T05:52:55.000Z","updated":"2021-02-21T12:40:58.749Z","comments":true,"path":"api/articles/博客同时部署到github和gitee.json","excerpt":null,"keywords":null,"cover":"/2021/01/%E5%8D%9A%E5%AE%A2%E5%90%8C%E6%97%B6%E9%83%A8%E7%BD%B2%E5%88%B0github%E5%92%8Cgitee/824531577.jpg","content":null,"raw":null,"categories":[{"name":"搭建博客","path":"api/categories/搭建博客.json"}],"tags":[{"name":"博客","path":"api/tags/博客.json"}]},{"title":"在Github上搭建静态博客","slug":"在Github上搭建静态博客","date":"2021-01-12T12:40:25.000Z","updated":"2021-01-28T02:04:54.557Z","comments":true,"path":"api/articles/在Github上搭建静态博客.json","excerpt":null,"keywords":null,"cover":"/2021/01/%E5%9C%A8Github%E4%B8%8A%E6%90%AD%E5%BB%BA%E9%9D%99%E6%80%81%E5%8D%9A%E5%AE%A2/2021-1-12-15-19.jpg","content":null,"raw":null,"categories":[{"name":"搭建博客","path":"api/categories/搭建博客.json"}],"tags":[{"name":"博客","path":"api/tags/博客.json"}]},{"title":"对Next主题进行详细配置","slug":"对Next主题进行详细配置","date":"2021-01-15T02:46:37.000Z","updated":"2021-01-28T02:08:23.590Z","comments":true,"path":"api/articles/对Next主题进行详细配置.json","excerpt":null,"keywords":null,"cover":"/2021/01/%E5%AF%B9Next%E4%B8%BB%E9%A2%98%E8%BF%9B%E8%A1%8C%E8%AF%A6%E7%BB%86%E9%85%8D%E7%BD%AE/tmp_img0113_175112.png","content":null,"raw":null,"categories":[{"name":"搭建博客","path":"api/categories/搭建博客.json"}],"tags":[{"name":"博客","path":"api/tags/博客.json"},{"name":"美化","path":"api/tags/美化.json"},{"name":"前端","path":"api/tags/前端.json"}]},{"title":"解决hexo一些问题","slug":"解决hexo一些问题","date":"2021-01-13T08:58:00.000Z","updated":"2021-02-03T11:20:57.429Z","comments":true,"path":"api/articles/解决hexo一些问题.json","excerpt":null,"keywords":null,"cover":"/2021/01/%E8%A7%A3%E5%86%B3hexo%E4%B8%80%E4%BA%9B%E9%97%AE%E9%A2%98/2021-1-13-16-33.jpg","content":null,"raw":null,"categories":[{"name":"搭建博客","path":"api/categories/搭建博客.json"}],"tags":[{"name":"解决问题","path":"api/tags/解决问题.json"},{"name":"博客","path":"api/tags/博客.json"}]},{"title":"关于我博客移植到小程序上的那些事","slug":"关于我博客移植到小程序上的那些事","date":"2021-05-17T00:55:13.000Z","updated":"2021-05-17T08:20:37.431Z","comments":true,"path":"api/articles/关于我博客移植到小程序上的那些事.json","excerpt":null,"keywords":null,"cover":"/2021/05/%E5%85%B3%E4%BA%8E%E6%88%91%E5%8D%9A%E5%AE%A2%E7%A7%BB%E6%A4%8D%E5%88%B0%E5%B0%8F%E7%A8%8B%E5%BA%8F%E4%B8%8A%E7%9A%84%E9%82%A3%E4%BA%9B%E4%BA%8B/fc3cd489ab144017a145f2d3170w.jpg","content":null,"raw":null,"categories":[{"name":"搭建博客","path":"api/categories/搭建博客.json"}],"tags":[{"name":"博客","path":"api/tags/博客.json"},{"name":"前端","path":"api/tags/前端.json"}]}]}